forex_data/__init__.py
forex_data/portfolio.py
forex_data/portfolio_hw1.py
forex_data/portfolio_hw2&3.py
forex_data/return_classes.py
forex_data-0.3.0.dist-info/METADATA
forex_data-0.3.0.dist-info/WHEEL
forex_data-0.3.0.dist-info/top_level.txt
forex_data-0.3.0.dist-info/RECORD
