Metadata-Version: 2.1
Name: forex-data
Version: 0.3.0
Summary: Demo library
Home-page: https://forex-data.readthedocs.io/
Author: Kyra Zhang & Max
Author-email: xz3036@nyu.edu
License: MIT
Platform: UNKNOWN
Classifier: Intended Audience :: Developers
Classifier: License :: OSI Approved :: MIT License
Classifier: Programming Language :: Python
Classifier: Programming Language :: Python :: 3
Classifier: Programming Language :: Python :: 3.6
Classifier: Programming Language :: Python :: 3.7
Classifier: Programming Language :: Python :: 3.8
Classifier: Programming Language :: Python :: 3.9
Classifier: Operating System :: OS Independent
Requires-Dist: numpy
Requires-Dist: polygon
Requires-Dist: pandas
Requires-Dist: sqlalchemy
